[
  {
    "id": "manga_yuri",
    "type": "BOOK",
    "name": "yuri doujin",
    "description": "A heartwarming tale of love between girls. It assumes the reader is already familiar with the characters, so it can get right into making them kiss. Read from right to left.",
    "weight": 180,
    "volume": 1,
    "price": 2370,
    "material": [ "paper" ],
    "symbol": "?",
    "color": "light_blue",
    "intelligence": 6,
    "time": 15,
    "chapters": 36,
    "fun": 4,
    "flags": ["INSPIRATIONAL"]
  },
	{
    "id": "manga_hentai",
    "type": "BOOK",
    "name": "hentai doujin",
    "description": "Low-grade graphical smut. Most of the enjoyment is in the absurd dialogue.",
    "weight": 120,
    "volume": 1,
    "price": 1650,
    "material": [ "paper" ],
    "symbol": "?",
    "color": "light_cyan",
    "intelligence": 1,
    "time": 8,
    "chapters": 12,
    "fun": 1
  },
	{
    "id": "manga_hentai_kinky",
    "type": "BOOK",
    "name": "kinky doujin",
    "description": "A rare gem of graphical smut, featuring all the good kinks and none of the bad kinks. What every lewd doujin should be, in your opinion.",
    "weight": 230,
    "volume": 1,
    "price": 1950,
    "material": [ "paper" ],
    "symbol": "?",
    "color": "light_cyan",
    "intelligence": 6,
    "time": 18,
    "chapters": 18,
    "fun": 4
  },
  {
    "id": "manual_wife",
    "name": "The Heart of War",
    "name_plural": "The Heart of War",
    "description": "The famous book by Sun Tsun, with annotations on how to apply its advice in modern times. These tips also illustrate the essentials of Wife-Fu.",
    "type": "GENERIC",
    "category": "books",
    "symbol": "?",
    "color": "green",
    "price": 20000,
    "material": "paper",
    "weight": 150,
    "volume": 1,
    "use_action": "MA_MANUAL",
    "book_data": {
      "max_level" : 0,
      "time" : 10,
      "fun" : 2,
      "skill" : "none",
      "required_level" : 0
    }
  },
  {
    "id": "book_tablet_joke",
    "type": "BOOK",
    "name": "stone tablet of knock-knock jokes",
    "description": "Lowbrow humor from ancient Samothrace. Surprisingly funny, if you're the sort of person that knows how to read dead languages.",
    "weight": 2300,
    "volume": 4,
    "price": 6500,
    "material": [ "stone" ],
    "symbol": "?",
    "color": "light_blue",
    "intelligence": 17,
    "time": 46,
    "chapters": 24,
    "fun": 3
  },
  {
    "id": "textbook_maid",
    "name": "Maid in Heaven",
    "name_plural": "Maid in Heaven",
    "description": "A reference guide by and for maids of a certain persuasion. While originally intended for more-or-less leisurely pursuits, it might give you some more practical ideas as well.",
    "type": "BOOK",
    "category": "books",
    "symbol": "?",
    "color": "green",
    "price": 20000,
    "material": "paper",
    "weight": 350,
    "volume": 2,
    "skill" : "tailor",
    "required_level" : 3,
    "max_level" : 5,
    "intelligence" : 5,
    "time" : 30,
    "fun" : 2
  },
  {
    "id": "catalog_necaux",
    "name": "Necaux Labs Catalog",
    "description": "A mail-order catalog for Necaux Labs' products. This one is the swimsuit edition.",
    "type": "BOOK",
    "category": "books",
    "symbol": "?",
    "color": "light_cyan",
    "price": 1700,
    "material": "paper",
    "weight": 150,
    "volume": 1,
    "time": 19,
    "fun": 2
  }
]